symantex/__init__.py
symantex/_patches.py
symantex/core.py
symantex/errors.py
symantex/factory.py
symantex/registry.py
symantex-0.3.0.dist-info/licenses/LICENSE
symantex-0.3.0.dist-info/METADATA
symantex-0.3.0.dist-info/WHEEL
symantex-0.3.0.dist-info/top_level.txt
symantex-0.3.0.dist-info/RECORD
