Metadata-Version: 2.4
Name: symantex
Version: 0.3.0
Summary: Thin python interface for using Large Language Models to convert LaTeX into Sympy for automatic mathematical processing
Author-email: "Nicholas Roy / FormuLearn B.V." <nicholas.roy@formulearn.org>
License-Expression: GPL-3.0-only
Project-URL: Homepage, https://github.com/FormuLearn/Symantex
Project-URL: Issues, https://github.com/FormuLearn/Symantex/issues
Classifier: Programming Language :: Python :: 3
Classifier: Operating System :: OS Independent
Requires-Python: >=3.10
License-File: LICENSE
Requires-Dist: sympy<2,>=1.14
Requires-Dist: mirascope[openai]>=1.25
Dynamic: license-file
